[
  
 {
    "key": "CheckboxTerms",
    "type": "checkbox",
    "templateOptions": {
      "label": "Accept terms ",
      "description": "Italiapt terms",
      "pattern": "true",
      "required": true
    }
  },


   {
    "key": "CheckboxTerms3",
    "type": "checkbox-italia",
    "templateOptions": {
      "label": "Accept terms 3 ",
      "default" : false,
      "description": "Itali3apt terms",
      "required": true
    }
  },

   {
      "key": "iban",
      "type": "input",
      "templateOptions": {
        "label": "iban"
      }
    }

]